wsidicom/__init__.py
wsidicom/cache.py
wsidicom/conceptcode.py
wsidicom/config.py
wsidicom/errors.py
wsidicom/geometry.py
wsidicom/graphical_annotations.py
wsidicom/source.py
wsidicom/stringprinting.py
wsidicom/tags.py
wsidicom/target.py
wsidicom/thread.py
wsidicom/uid.py
wsidicom/wsidicom.py
wsidicom/codec/__init__.py
wsidicom/codec/codec.py
wsidicom/codec/decoder.py
wsidicom/codec/encoder.py
wsidicom/codec/media_types.py
wsidicom/codec/optionals.py
wsidicom/codec/rle.py
wsidicom/codec/settings.py
wsidicom/file/__init__.py
wsidicom/file/wsidicom_file_image_data.py
wsidicom/file/wsidicom_file_source.py
wsidicom/file/wsidicom_file_target.py
wsidicom/file/wsidicom_stream_opener.py
wsidicom/file/io/__init__.py
wsidicom/file/io/wsidicom_io.py
wsidicom/file/io/wsidicom_reader.py
wsidicom/file/io/wsidicom_writer.py
wsidicom/file/io/frame_index/__init__.py
wsidicom/file/io/frame_index/basic.py
wsidicom/file/io/frame_index/encapsulated_pixel_data.py
wsidicom/file/io/frame_index/extended.py
wsidicom/file/io/frame_index/native_pixel_data.py
wsidicom/file/io/frame_index/offset_table.py
wsidicom/file/io/frame_index/offset_table_type.py
wsidicom/file/io/frame_index/offset_table_writer.py
wsidicom/file/io/frame_index/parser.py
wsidicom/file/io/frame_index/pixel_data.py
wsidicom/file/io/frame_index/tiff.py
wsidicom/group/__init__.py
wsidicom/group/group.py
wsidicom/group/level.py
wsidicom/instance/__init__.py
wsidicom/instance/dataset.py
wsidicom/instance/image_data.py
wsidicom/instance/instance.py
wsidicom/instance/pillow_image_data.py
wsidicom/instance/wsidicom_image_data.py
wsidicom/instance/tile_index/__init__.py
wsidicom/instance/tile_index/full_tile_index.py
wsidicom/instance/tile_index/sparse_tile_index.py
wsidicom/instance/tile_index/tile_index.py
wsidicom/metadata/__init__.py
wsidicom/metadata/equipment.py
wsidicom/metadata/image.py
wsidicom/metadata/label.py
wsidicom/metadata/optical_path.py
wsidicom/metadata/overview.py
wsidicom/metadata/patient.py
wsidicom-0.29.0.dist-info/METADATA
wsidicom-0.29.0.dist-info/WHEEL
wsidicom-0.29.0.dist-info/licenses/LICENCE
wsidicom-0.29.0.dist-info/RECORD
