Metadata-Version: 2.4
Name: wsidicom
Version: 0.29.0
Summary: Tools for handling DICOM based whole scan images
Project-URL: Repository, https://github.com/imi-bigpicture/wsidicom
Author-email: Erik O Gabrielsson <erik.o.gabrielsson@sectra.com>
License: Apache-2.0
License-File: LICENCE
Keywords: annotations,dicom,digital pathology,whole slide image
Classifier: Development Status :: 4 - Beta
Classifier: Intended Audience :: Developers
Classifier: Intended Audience :: Healthcare Industry
Classifier: Intended Audience :: Science/Research
Classifier: Operating System :: OS Independent
Classifier: Topic :: Scientific/Engineering :: Medical Science Apps.
Requires-Python: >=3.10
Requires-Dist: dicomweb-client<0.60.0,>=0.59.2
Requires-Dist: fsspec>=2024.2.0
Requires-Dist: marshmallow<4.0.0,>=3.20.1
Requires-Dist: numpy>=1.22.0
Requires-Dist: pillow>=9.1.1
Requires-Dist: pydicom>=3.0.0
Requires-Dist: universal-pathlib<0.3.0,>=0.2.1
Provides-Extra: imagecodecs
Requires-Dist: imagecodecs!=2024.9.22,<2025.0.0,>=2024.1.1; extra == 'imagecodecs'
Provides-Extra: pyjpegls
Requires-Dist: pyjpegls<2.0.0,>=1.2.0; extra == 'pyjpegls'
Provides-Extra: pylibjpeg-openjpeg
Requires-Dist: pylibjpeg-openjpeg<3.0.0,>=2.1.1; extra == 'pylibjpeg-openjpeg'
Provides-Extra: pylibjpeg-rle
Requires-Dist: pylibjpeg-rle<3.0.0,>=2.0.0; extra == 'pylibjpeg-rle'
